{"inkVersion":20,"root":[["^Dag 1 : Net zes uur gewerkt, 48 euro in de pocket! ",{"#":"speaker Steve"},"\n","^Dag 3 : Vroeg opstaan om tot 18:00 te werken, geen zin maar ik kom er wel door! ",{"#":"speaker Steve"},"\n","^Dag 8  Zo moe, maar nog twee uurtjes dan ben ik vrij. ",{"#":"speaker Steve"},"\n","^Dag 14  Nog drie uur... ",{"#":"speaker Steve"},"\n","^2 patat middel, een bak kipnuggets en een hamburger double jerky Steve. ",{"#":"speaker Mike"},"\n","^Steve? ",{"#":"speaker Mike"},"\n","^Hey Steve. ",{"#":"speaker Mike"},"\n","^Mike knipte zijn vingers voor Steves ogen.","\n","^Huh wat? Oh. ",{"#":"speaker Steve"},"\n","^Gaat het wel jongen? Je bent spierwit Kom. ",{"#":"speaker Mike"},"\n","done",["done",{"#f":5,"#n":"g-0"}],null],"done",{"#f":1}],"listDefs":{}}